pydagogy_brent/__init__.py
pydagogy_brent-0.0.1.dist-info/WHEEL
pydagogy_brent-0.0.1.dist-info/METADATA
pydagogy_brent-0.0.1.dist-info/RECORD
