Metadata-Version: 2.1
Name: pydagogy-brent
Version: 0.0.1
Summary: Brent's algorithm
Home-page: https://github.com/denisrosset/brent-level-2.git
License: MIT
Author: Denis Rosset
Author-email: physics@denisrosset.com
Requires-Python: >=3.8,<4.0
Classifier: License :: OSI Approved :: MIT License
Classifier: Programming Language :: Python :: 3
Classifier: Programming Language :: Python :: 3.10
Classifier: Programming Language :: Python :: 3.8
Classifier: Programming Language :: Python :: 3.9
Requires-Dist: rich (>=12.0.0,<13.0.0)
Project-URL: Repository, https://github.com/denisrosset/brent-level-2.git
